pyG2/G2.py
pyG2/__init__.py
pyG2/g2/__init__.py
pyG2/g2/g2.min.js
pyG2-1.0b1.dist-info/LICENSE
pyG2-1.0b1.dist-info/METADATA
pyG2-1.0b1.dist-info/WHEEL
pyG2-1.0b1.dist-info/top_level.txt
pyG2-1.0b1.dist-info/RECORD
