Metadata-Version: 2.1
Name: pyG2
Version: 1.0b1
Summary: Grammar of graphics for python
Home-page: https://github.com/ThamaluM/pyG2
Author: Thamalu Maliththa Piyadigama
License: UNKNOWN
Platform: UNKNOWN
Classifier: Programming Language :: Python 
Classifier: License :: OSI Approved :: MIT License
Classifier: Operating System :: OS Independent
Requires-Dist: ipython
Requires-Dist: pandas
